import_string/__init__.py
import_string/base.py
import_string-0.1.0.dist-info/DESCRIPTION.rst
import_string-0.1.0.dist-info/METADATA
import_string-0.1.0.dist-info/RECORD
import_string-0.1.0.dist-info/WHEEL
import_string-0.1.0.dist-info/metadata.json
import_string-0.1.0.dist-info/top_level.txt
