Metadata-Version: 1.1
Name: import_string
Version: 0.1.0
Summary: Imports an object based on a string
Home-page: https://github.com/rochacbruno/import_string
Author: Bruno Rocha
Author-email: rochacbruno@gmail.com
License: ISC license
Keywords: import_string
Platform: UNKNOWN
Classifier: Development Status :: 2 - Pre-Alpha
Classifier: Intended Audience :: Developers
Classifier: License :: OSI Approved :: ISC License (ISCL)
Classifier: Natural Language :: English
Classifier: Programming Language :: Python :: 2
Classifier: Programming Language :: Python :: 2.6
Classifier: Programming Language :: Python :: 2.7
Classifier: Programming Language :: Python :: 3
Classifier: Programming Language :: Python :: 3.3
Classifier: Programming Language :: Python :: 3.4
Classifier: Programming Language :: Python :: 3.5
